Disecon/__init__.py
Disecon/bank.py
Disecon/money.py
Disecon/results.py
Disecon/start.py
Disecon/top.py
Disecon/view.py
Disecon/wallet.py
Disecon-1.0.0.dist-info/LICENSE
Disecon-1.0.0.dist-info/METADATA
Disecon-1.0.0.dist-info/WHEEL
Disecon-1.0.0.dist-info/top_level.txt
Disecon-1.0.0.dist-info/RECORD
