Metadata-Version: 2.1
Name: Disecon
Version: 1.0.0
Summary: Disecon
Home-page: https://github.com/Mason-Dino/Disecon
Author: LegosAndStuff
License: MIT
Keywords: economy
Classifier: Development Status :: 5 - Production/Stable
Classifier: Intended Audience :: Developers
Classifier: Operating System :: OS Independent
Classifier: License :: OSI Approved :: MIT License
Classifier: Programming Language :: Python :: 3.12
License-File: LICENSE
